{"v":4,"entries":{"colors--docs":{"id":"colors--docs","title":"Colors","name":"Docs","importPath":"./src/components/atoms/Colors/Colors.mdx","storiesImports":[],"type":"docs","tags":["unattached-mdx","docs"]},"mform--docs":{"id":"mform--docs","title":"MForm","name":"Docs","importPath":"./src/components/atoms/Form/MForm.mdx","storiesImports":[],"type":"docs","tags":["unattached-mdx","docs"]},"atoms-button--docs":{"id":"atoms-button--docs","title":"Atoms/Button","name":"Docs","importPath":"./src/components/atoms/Button/Button.stories.ts","type":"docs","tags":["autodocs","docs"],"storiesImports":[]},"atoms-button--primary":{"type":"story","id":"atoms-button--primary","name":"Primary","title":"Atoms/Button","importPath":"./src/components/atoms/Button/Button.stories.ts","tags":["autodocs","story"]},"atoms-input--docs":{"id":"atoms-input--docs","title":"Atoms/Input","name":"Docs","importPath":"./src/components/atoms/Input/Input.stories.tsx","type":"docs","tags":["autodocs","docs"],"storiesImports":[]},"atoms-input--basic":{"type":"story","id":"atoms-input--basic","name":"Basic","title":"Atoms/Input","importPath":"./src/components/atoms/Input/Input.stories.tsx","tags":["autodocs","story"]}}}
